django_haystackbrowser-0.6.3.dist-info/LICENSE.txt
django_haystackbrowser-0.6.3.dist-info/METADATA
django_haystackbrowser-0.6.3.dist-info/RECORD
django_haystackbrowser-0.6.3.dist-info/WHEEL
django_haystackbrowser-0.6.3.dist-info/top_level.txt
haystackbrowser/__init__.py
haystackbrowser/admin.py
haystackbrowser/forms.py
haystackbrowser/models.py
haystackbrowser/test_admin.py
haystackbrowser/test_app.py
haystackbrowser/test_config.py
haystackbrowser/test_forms.py
haystackbrowser/tests_compat.py
haystackbrowser/utils.py
haystackbrowser/templates/admin/haystackbrowser/change_form_with_data.html
haystackbrowser/templates/admin/haystackbrowser/change_form_with_link.html
haystackbrowser/templates/admin/haystackbrowser/result.html
haystackbrowser/templates/admin/haystackbrowser/result_list.html
haystackbrowser/templates/admin/haystackbrowser/result_list_headers.html
haystackbrowser/templates/admin/haystackbrowser/view.html
haystackbrowser/templates/admin/haystackbrowser/view_data.html
haystackbrowser/templatetags/__init__.py
haystackbrowser/templatetags/haystackbrowser_compat.py
haystackbrowser/templatetags/haystackbrowser_data.py
