Metadata-Version: 2.1
Name: django-haystackbrowser
Version: 0.6.3
Summary: A reusable Django application for viewing and debugging all the data that has been pushed into Haystack
Home-page: https://github.com/kezabelle/django-haystackbrowser/tree/master
Author: Keryn Knight
Author-email: python-package@kerynknight.com
License: BSD License
Keywords: django
Platform: OS Independent
Classifier: Development Status :: 4 - Beta
Classifier: Environment :: Web Environment
Classifier: Framework :: Django
Classifier: Intended Audience :: Developers
Classifier: Operating System :: OS Independent
Classifier: Programming Language :: Python :: 2.6
Classifier: Programming Language :: Python :: 2.7
Classifier: Programming Language :: Python :: 3.3
Classifier: Programming Language :: Python :: 3.4
Classifier: Programming Language :: Python :: 3.5
Classifier: Natural Language :: English
Classifier: Topic :: Internet :: WWW/HTTP :: Site Management
Classifier: Topic :: Database :: Front-Ends
Classifier: License :: OSI Approved :: BSD License
Classifier: Framework :: Django
Classifier: Framework :: Django :: 1.4
Classifier: Framework :: Django :: 1.5
Classifier: Framework :: Django :: 1.6
Classifier: Framework :: Django :: 1.7
Classifier: Framework :: Django :: 1.8
Requires-Dist: django-classy-tags (>=0.3.4.1)
Requires-Dist: django-haystack (>=1.2.0)
